wrpclient/__init__.py
wrpclient/__main__.py
wrpclient/camera.py
wrpclient/client.py
wrpclient/driver.py
wrpclient/message.py
wrpclient/wrp_connector.py
wrpclient-0.1.dist-info/LICENSE
wrpclient-0.1.dist-info/METADATA
wrpclient-0.1.dist-info/WHEEL
wrpclient-0.1.dist-info/top_level.txt
wrpclient-0.1.dist-info/RECORD
