Metadata-Version: 2.1
Name: wrpclient
Version: 0.1
Summary: Workswell Remote Protocol Client
Home-page: https://github.com/Kasape/wrpclient
Author: Petr Kasalický
Author-email: kasape@atlas.cz
License: GNU GPLv3 License
Keywords: thermal,infrared,camera,workswell,remote,protocol,client
Platform: UNKNOWN
Classifier: Intended Audience :: Developers
Classifier: License :: OSI Approved :: GNU General Public License v3 (GPLv3)
Classifier: Operating System :: OS Independent
Classifier: Programming Language :: Python
Classifier: Programming Language :: Python :: 3
Classifier: Programming Language :: Python :: 3.6
Classifier: Programming Language :: Python :: 3.7
Classifier: Topic :: Multimedia :: Graphics :: Capture :: Digital Camera
Classifier: Topic :: Multimedia :: Video :: Capture
Classifier: Topic :: Scientific/Engineering :: Image Recognition
Classifier: Topic :: Scientific/Engineering :: Visualization
Classifier: Topic :: Software Development :: Libraries :: Python Modules
Classifier: Framework :: IPython
Classifier: Framework :: AsyncIO
Requires-Python: >=3.6
Requires-Dist: numpy
